LICENSE
LICENSE-dpy
MANIFEST.in
README.md
pyproject.toml
ampapi/__init__.py
ampapi/adsmodule.py
ampapi/analytics.py
ampapi/backoff.py
ampapi/base.py
ampapi/bridge.py
ampapi/controller.py
ampapi/core.py
ampapi/emailsender.py
ampapi/enums_.py
ampapi/filebackup.py
ampapi/filemanager.py
ampapi/instance.py
ampapi/minecraft.py
ampapi/modules.py
ampapi/types_.py
ampapi/util.py
cc_ampapi.egg-info/PKG-INFO
cc_ampapi.egg-info/SOURCES.txt
cc_ampapi.egg-info/dependency_links.txt
cc_ampapi.egg-info/requires.txt
cc_ampapi.egg-info/top_level.txt