Metadata-Version: 2.4
Name: cc-ampapi
Version: 4.6.0
Summary: A Python wrapper for the AMP API by CubeCoders
Author-email: k8thekat <Cadwalladerkatelynn+AMPAPI@gmail.com>
License:                     GNU GENERAL PUBLIC LICENSE
Project-URL: GitHub, https://github.com/k8thekat/AMPAPI_Python
Project-URL: Changelog, https://github.com/k8thekat/AMPAPI_Python/blob/master/CHANGELOG.md
Keywords: cubecoders,cube coders,amp,api
Classifier: Development Status :: 5 - Production/Stable
Classifier: Intended Audience :: Developers
Classifier: License :: OSI Approved :: GNU General Public License v3 or later (GPLv3+)
Classifier: Operating System :: OS Independent
Classifier: Programming Language :: Python :: 3.10
Classifier: Programming Language :: Python :: 3.11
Classifier: Programming Language :: Python :: 3.12
Classifier: Framework :: AsyncIO
Classifier: Topic :: Internet
Classifier: Topic :: Software Development :: Libraries
Classifier: Topic :: Software Development :: Libraries :: Python Modules
Classifier: Topic :: Utilities
Classifier: Typing :: Typed
Requires-Python: >=3.10.0
License-File: LICENSE
License-File: LICENSE-dpy
Requires-Dist: aiohttp>=3.7.4.post0
Requires-Dist: dataclass-wizard>=0.22.2
Requires-Dist: pyotp>=2.6.0
Dynamic: license-file
